{
  "id": "foi-act-2011",
  "type": "statute",
  "title": "Freedom of Information Act 2011",
  "title_en": "Freedom of Information Act 2011",
  "short_name": "FOI Act 2011",
  "status": "in_force",
  "issued_date": "2011-05-28",
  "in_force_date": "2011-05-28",
  "url": "https://nigerialii.org/akn/ng/act/2011/4/eng%402011-05-28",
  "description": "Right of access to public records and information; relevant for transparency and data governance. SOURCE UNAVAILABLE: NigeriaLII AKN URL returns 404 (2026-02-19)",
  "provisions": [],
  "definitions": []
}